marvelrivalsapi/__init__.py
marvelrivalsapi/async_client.py
marvelrivalsapi/client.py
marvelrivalsapi/models.py
marvelrivalsapi/utility.py
marvelrivalsapi-0.1.0a0.dist-info/LICENSE
marvelrivalsapi-0.1.0a0.dist-info/METADATA
marvelrivalsapi-0.1.0a0.dist-info/WHEEL
marvelrivalsapi-0.1.0a0.dist-info/RECORD
