Metadata-Version: 2.3
Name: marvelrivalsapi
Version: 0.1.0a0
Summary: 
License: MIT License
Author: externref
Author-email: shiva02939@gmail.com
Requires-Python: >=3.9.0
Classifier: License :: Other/Proprietary License
Classifier: Programming Language :: Python :: 3
Classifier: Programming Language :: Python :: 3.9
Classifier: Programming Language :: Python :: 3.10
Classifier: Programming Language :: Python :: 3.11
Classifier: Programming Language :: Python :: 3.12
Classifier: Programming Language :: Python :: 3.13
Requires-Dist: attrs (>=25.3.0,<26.0.0)
Requires-Dist: httpx (>=0.28.1,<0.29.0)
Requires-Dist: pygments (>=2.19.1,<3.0.0)
